geo_track_analyzer/__init__.py
geo_track_analyzer/compare.py
geo_track_analyzer/enhancer.py
geo_track_analyzer/exceptions.py
geo_track_analyzer/model.py
geo_track_analyzer/processing.py
geo_track_analyzer/track.py
geo_track_analyzer/cli/__init__.py
geo_track_analyzer/cli/_extract_track.py
geo_track_analyzer/cli/_update_elevation.py
geo_track_analyzer/postgis/__init__.py
geo_track_analyzer/postgis/db.py
geo_track_analyzer/utils/__init__.py
geo_track_analyzer/utils/base.py
geo_track_analyzer/utils/internal.py
geo_track_analyzer/utils/model.py
geo_track_analyzer/utils/track.py
geo_track_analyzer/visualize/__init__.py
geo_track_analyzer/visualize/constants.py
geo_track_analyzer/visualize/interactive.py
geo_track_analyzer/visualize/map.py
geo_track_analyzer/visualize/metrics.py
geo_track_analyzer/visualize/profiles.py
geo_track_analyzer/visualize/summary.py
geo_track_analyzer/visualize/utils.py
geo_track_analyzer-1.7.0.dist-info/entry_points.txt
geo_track_analyzer-1.7.0.dist-info/licenses/LICENSE
geo_track_analyzer-1.7.0.dist-info/WHEEL
geo_track_analyzer-1.7.0.dist-info/METADATA
geo_track_analyzer-1.7.0.dist-info/RECORD
