Metadata-Version: 2.4
Name: geo-track-analyzer
Version: 1.7.0
Summary: Analyze geospacial data tracks
Keywords: fit,gpx,visualization,analysis
Author-email: Korbinian Schweiger <korbinian.schweiger@gmail.com>
Requires-Python: >=3.11
Classifier: License :: OSI Approved :: MIT License
Classifier: Topic :: Scientific/Engineering :: GIS
Classifier: Topic :: Scientific/Engineering :: Visualization
Classifier: Topic :: Software Development :: Libraries
Classifier: Programming Language :: Python
Classifier: Programming Language :: Python :: 3.10
Classifier: Programming Language :: Python :: 3.11
Classifier: Programming Language :: Python :: 3.12
Classifier: Programming Language :: Python :: 3.13
Classifier: Programming Language :: Python :: 3 :: Only
License-File: LICENSE
Requires-Dist: numpy>=1,<2
Requires-Dist: gpxpy~=1.6
Requires-Dist: requests>=2,<3
Requires-Dist: plotly>=5,<6
Requires-Dist: pandas>=2,<3
Requires-Dist: fitparse~=1.2
Requires-Dist: pydantic>=2,<3
Requires-Dist: pydantic-numpy>=5,<6
Requires-Dist: click>=8,<9 ; extra == "cli"
Requires-Dist: rich ; extra == "cli"
Requires-Dist: geo-track-analyzer[cli, postgis] ; extra == "full"
Requires-Dist: psycopg2 ; extra == "full"
Requires-Dist: SQLAlchemy ; extra == "postgis"
Project-URL: Documentation, https://kschweiger.github.io/track_analyzer/
Project-URL: Home, https://github.com/kschweiger/track_analyzer
Project-URL: Source, https://github.com/kschweiger/track_analyzer
Provides-Extra: cli
Provides-Extra: full
Provides-Extra: postgis
